lambda_sigterm/__init__.py
lambda_sigterm-0.1.2.dist-info/METADATA
lambda_sigterm-0.1.2.dist-info/WHEEL
lambda_sigterm-0.1.2.dist-info/licenses/LICENSE
lambda_sigterm-0.1.2.dist-info/RECORD
