Metadata-Version: 2.1
Name: lambda_sigterm
Version: 0.1.2
Summary: Creates a noop Lambda Extension which allows Lambda to receive SIGTERM events
Project-URL: Homepage, https://github.com/lorenmh/lambda-sigterm
Project-URL: Bug Tracker, https://github.com/lorenmh/lambda-sigterm/issues
Author-email: Loren Howard <loren@plutonium.io>
License: MIT License
License-File: LICENSE
Classifier: License :: OSI Approved :: MIT License
Classifier: Operating System :: OS Independent
Classifier: Programming Language :: Python :: 3
Requires-Python: >=3.7
